{
  "kind": "collectionType",
  "collectionName": "collections",
  "info": {
    "singularName": "collection",
    "pluralName": "collections",
    "displayName": "collection"
  },
  "options": {
    "draftAndPublish": false
  },
  "pluginOptions": {},
  "attributes": {
    "client": {
      "type": "relation",
      "relation": "oneToOne",
      "target": "api::client.client"
    },
    "waste": {
      "type": "string"
    },
    "colector": {
      "allowedTypes": [
        "images",
        "files",
        "videos",
        "audios"
      ],
      "type": "media",
      "multiple": false
    },
    "weight": {
      "type": "string"
    },
    "breakdown": {
      "allowedTypes": [
        "images",
        "files",
        "videos",
        "audios"
      ],
      "type": "media",
      "multiple": true
    }
  }
}
